{"chromosome": "chr18", "target_5p": [14821956, 14822956], "target_3p": [14822956, 14823956], "window": 5, "me_strand": "+", "me_start": 2626, "me_end": 6018, "pred": "5", "regions": [{"name": "5P Insertion Site", "x": [1000, 1], "color": "#0000FF"}, {"name": "3P Insertion Site", "x": [4391, 1], "color": "#0000FF"}, {"name": "5P TSD", "x": [995, 5], "color": "#48c2e0"}, {"name": "3P TSD", "x": [4392, 5], "color": "#48c2e0"}], "type": "melt", "info": {"TSD": "GTTTT", "ASSESS": "5", "INTERNAL": "NM_001145029,INTRONIC", "SVTYPE": "LINE1", "SVLEN": "3392", "MEINFO": "L1Ambig,2626,6018,+", "DIFF": "0.04:n1-3381,n3389,g3396a,a3408g,c3423a,t3428g,c3429t,t3430a,g3437c,g3438a,t3443g,g3447a,c3451t,t3460a,t3465a,c3477t,t3481a,c3482t,c3510a,a3526t,t3534c,g3550a,g3556c,c3560t,i3565a,a3612t,c3669t,t3686c,c3718t,g3733a,g3754a,n3760-6019", "LP": "1", "RP": "7", "RA": "-2.807", "ISTP": "0", "PRIOR": "false", "SR": "2"}, "read_length": 250}