{"chromosome": "chr18", "target_5p": [53898373, 53899373], "target_3p": [53899373, 53900373], "window": 18, "me_strand": "-", "me_start": 0, "me_end": 6019, "pred": "5", "regions": [{"name": "5P Insertion Site", "x": [1000, 1], "color": "#0000FF"}, {"name": "3P Insertion Site", "x": [7018, 1], "color": "#0000FF"}, {"name": "5P TSD", "x": [982, 18], "color": "#48c2e0"}, {"name": "3P TSD", "x": [7019, 18], "color": "#48c2e0"}], "type": "melt", "info": {"TSD": "CAAAAGAAATATATTTTT", "ASSESS": "5", "INTERNAL": "null,null", "SVTYPE": "LINE1", "SVLEN": "6019", "MEINFO": "L1Ambig,0,6019,-", "DIFF": "0.09:n1-3,i72g,c72g,c102t,t149g,t153c,t162g,c205t,c224a,t231c,t254a,g313a,c324g,c351t,c418t,a423g,g483a,g605a,n624-6019", "LP": "25", "RP": "31", "RA": "-0.31", "ISTP": "0", "PRIOR": "false", "SR": "53"}, "read_length": 250}