{"chromosome": "chr10", "target_5p": [21084968, 21085968], "target_3p": [21085968, 21086968], "window": 0, "me_strand": "-", "me_start": 5666, "me_end": 6018, "pred": "4", "regions": [{"name": "5P Insertion Site", "x": [1000, 1], "color": "#0000FF"}, {"name": "3P Insertion Site", "x": [1351, 1], "color": "#0000FF"}], "type": "melt", "info": {"TSD": "null", "ASSESS": "4", "INTERNAL": "NM_213569,INTRONIC", "SVTYPE": "LINE1", "SVLEN": "352", "MEINFO": "L1Ta,5666,6018,-", "DIFF": "0.06:n1-5665", "LP": "8", "RP": "1", "RA": "3", "ISTP": "0", "PRIOR": "false", "SR": "3"}, "read_length": 250}