{"chromosome": "chr4", "target_5p": [79846387, 79847387], "target_3p": [79847387, 79848387], "window": 2, "me_strand": "+", "me_start": 5400, "me_end": 6019, "pred": "5", "regions": [{"name": "5P Insertion Site", "x": [1000, 1], "color": "#0000FF"}, {"name": "3P Insertion Site", "x": [1618, 1], "color": "#0000FF"}, {"name": "5P TSD", "x": [998, 2], "color": "#48c2e0"}, {"name": "3P TSD", "x": [1619, 2], "color": "#48c2e0"}], "type": "melt", "info": {"TSD": "AA", "ASSESS": "5", "INTERNAL": "NR_026555,INTRONIC", "SVTYPE": "LINE1", "SVLEN": "619", "MEINFO": "L1Ta,5400,6019,+", "DIFF": "0.1:n1-5399,a5605g", "LP": "28", "RP": "13", "RA": "1.107", "ISTP": "0", "PRIOR": "false", "SR": "28"}, "read_length": 250}